{
  "news_id": "NEWS_20260425182638_7e27396e",
  "title": "Macroeconomic data better than expected, New Energy sector affected",
  "original_title": "Macroeconomic data better than expected, New Energy sector affected",
  "source": "\u540c\u82b1\u987a",
  "source_type": "\u8d22\u7ecf\u5a92\u4f53",
  "source_url": "https://example.com/news/NEWS_20260425182638_7e27396e",
  "publish_time": "2026-04-23T09:39:38.051750",
  "collect_time": "2026-04-25T18:26:38.051750",
  "summary": "Macroeconomic data better than expected, New Energy sector affected",
  "content": "Macroeconomic data better than expected, New Energy sector affected",
  "related_stocks": [
    {
      "stock_code": "002594",
      "stock_name": "BYD",
      "mention_type": "main target"
    }
  ],
  "category": {
    "primary": "\u516c\u53f8\u8d22\u62a5",
    "secondary": [
      "Technology"
    ],
    "tags": [
      "\u5229\u6da6",
      "\u8d22\u52a1\u6570\u636e"
    ]
  },
  "sentiment": {
    "overall": "negative",
    "score": 0.09,
    "reason": "\u516c\u53f8\u8d22\u62a5 related news"
  },
  "impact_level": "medium",
  "market_reaction_expected": "Expected to impact BYD and related sectors",
  "metadata": {
    "word_count": 67,
    "has_image": false,
    "is_original": true,
    "is_headline": true
  }
}