{
  "category": {
    "tags": [
      "\u6e2f\u80a1", 
      "\u7f8e\u80a1"
    ], 
    "primary": "\u56fd\u9645\u5e02\u573a", 
    "secondary": [
      "Finance"
    ]
  }, 
  "content": "International market rising, A-share Pharmaceutical sector fluctuates", 
  "publish_time": "2026-04-20T19:18:51.180000", 
  "sentiment": {
    "reason": "\u56fd\u9645\u5e02\u573a related news", 
    "score": -0.18, 
    "overall": "neutral"
  }, 
  "title": "International market rising, A-share Pharmaceutical sector fluctuates", 
  "original_title": "International market rising, A-share Pharmaceutical sector fluctuates", 
  "market_reaction_expected": "Expected to impact China Merchants Bank and related sectors", 
  "collect_time": "2026-04-25T16:46:51.180000", 
  "source_url": "https://example.com/news/NEWS_20260425164651_fdfbb627", 
  "news_id": "NEWS_20260425164651_fdfbb627", 
  "source": "\u7b2c\u4e00\u8d22\u7ecf", 
  "source_type": "\u8d22\u7ecf\u5a92\u4f53", 
  "impact_level": "low", 
  "summary": "International market rising, A-share Pharmaceutical sector fluctuates", 
  "metadata": {
    "is_headline": false, 
    "is_original": true, 
    "word_count": 69, 
    "has_image": true
  }, 
  "related_stocks": [
    {
      "mention_type": "main target", 
      "stock_name": "China Merchants Bank", 
      "stock_code": "600036"
    }
  ]
}